academics_reddit_scraper/__init__.py
academics_reddit_scraper/academics_reddit_scraper.py
academics_reddit_scraper/sentiment_analysis.py
academics_reddit_scraper-0.2.4.dist-info/LICENSE
academics_reddit_scraper-0.2.4.dist-info/METADATA
academics_reddit_scraper-0.2.4.dist-info/WHEEL
academics_reddit_scraper-0.2.4.dist-info/entry_points.txt
academics_reddit_scraper-0.2.4.dist-info/top_level.txt
academics_reddit_scraper-0.2.4.dist-info/RECORD
